{
    "version": "4.18.1",
    "description": "Download videos, playlists, channels and subtitles from YouTube, Facebook, Vimeo and other video sites in high quality.",
    "homepage": "https://www.4kdownload.com/products/product-videodownloader",
    "license": {
        "identifier": "Freeware",
        "url": "https://www.4kdownload.com/it/agreement/freeware"
    },
    "architecture": {
        "32bit": {
            "url": "https://dl.4kdownload.com/app/4kvideodownloader_4.18.1.zip",
            "hash": "f612c6c53c0931d38ddb61fc38e716e681f45b6fba65e2a452f95300f9dc2e78"
        },
        "64bit": {
            "url": "https://dl.4kdownload.com/app/4kvideodownloader_4.18.1_x64.zip",
            "hash": "1e9ccc1e0c87a0105ca293e9484eccf193ded03c8943c5179b4f91083c9d787b"
        }
    },
    "extract_dir": "4kvideodownloader",
    "shortcuts": [
        [
            "4kvideodownloader.exe",
            "4K Video Downloader"
        ]
    ],
    "checkver": {
        "regex": "4kvideodownloader_([\\d.]+)_"
    },
    "autoupdate": {
        "architecture": {
            "32bit": {
                "url": "https://dl.4kdownload.com/app/4kvideodownloader_$version.zip"
            },
            "64bit": {
                "url": "https://dl.4kdownload.com/app/4kvideodownloader_$version_x64.zip"
            }
        }
    }
}
