{
    "version": "3.14.3",
    "description": "Download audio in MP3, M4A, OGG from YouTube, Soundcloud, Vimeo, Instagram, Facebook, Dailymotion, Twitch and more.",
    "homepage": "https://www.4kdownload.com/products/product-youtubetomp3",
    "license": {
        "identifier": "Freeware",
        "url": "https://www.4kdownload.com/it/agreement/freeware"
    },
    "architecture": {
        "32bit": {
            "url": "https://dl.4kdownload.com/app/4kyoutubetomp3_3.14.3.zip",
            "hash": "aa3feece3477f55b95ecec2fd2a0e0bf868eab128d541ec6bd5abdb5cce331f1"
        },
        "64bit": {
            "url": "https://dl.4kdownload.com/app/4kyoutubetomp3_3.14.3_x64.zip",
            "hash": "a199b62b030211b83d664e666ac725b57217dbb5b0c899c95be30d41fd392dd6"
        }
    },
    "extract_dir": "4kyoutubetomp3",
    "shortcuts": [
        [
            "4kyoutubetomp3.exe",
            "4K YouTube to MP3"
        ]
    ],
    "checkver": {
        "regex": "4kyoutubetomp3_([\\d.]+)_"
    },
    "autoupdate": {
        "architecture": {
            "32bit": {
                "url": "https://dl.4kdownload.com/app/4kyoutubetomp3_$version.zip"
            },
            "64bit": {
                "url": "https://dl.4kdownload.com/app/4kyoutubetomp3_$version_x64.zip"
            }
        }
    }
}
